stpc-0.1.0a3.dist-info/METADATA
stpc-0.1.0a3.dist-info/WHEEL
stpc-0.1.0a3.dist-info/licenses/LICENSE
stpc/__init__.py
stpc/main.py
stpc/micro_logger.py
stpc/stpc.cp313-win_amd64.pyd
stpc/stpc.pyi
stpc/time_sync.py
stpc-0.1.0a3.dist-info/RECORD
