Metadata-Version: 2.4
Name: stpc
Version: 0.1.0a3
Classifier: Intended Audience :: Developers
Classifier: Intended Audience :: Information Technology
Classifier: License :: OSI Approved :: MIT License
Classifier: Programming Language :: Python :: 3.12
Classifier: Programming Language :: Rust
Classifier: Topic :: Security :: Cryptography
Classifier: Topic :: Software Development :: Libraries :: Python Modules
Requires-Dist: ntplib>=0.4.0
Requires-Dist: colorama>=0.4.0
License-File: LICENSE
Summary: Secure Transport Protocol Certificate (STPC) - Cryptographic certificate system with modern algorithms support
Keywords: cryptography,certificates,security,ed25519,falcon,post-quantum
Author-email: Konstantin Gorshkov <kostya_gorshkov_06@vk.com>
Maintainer-email: Konstantin Gorshkov <kostya_gorshkov_06@vk.com>
License: MIT
Requires-Python: >=3.12
